{"input_matrix": {"data": [[0.5, 0.3], [0.2, 0.6], [0.8, 0.1]], "columns": ["Criteria 1", "Criteria 2"], "index": ["A", "B", "C"]}, "polarity": ["+", "-"], "sensitivity_on": "no", "normalization": "minmax", "aggregation": "weighted_sum", "robustness_on": "no", "robustness_on_single_weights": "no", "robustness_on_all_weights": "no", "given_weights": [0.6, 0.4], "robustness_on_indicators": "no", "monte_carlo_runs": 1000, "num_cores": 2, "random_seed": 42, "marginal_distribution_for_each_indicator": "normal", "output_path": "mock_output/"}